{
  "name": "Beatrice Sparks",
  "age": 24,
  "address": {
    "street": "Wucopa Boulevard",
    "city": "Pahruse",
    "state": "CA",
    "zip": "63270"
  },
  "contact": {
    "phone": "(302) 366-9663",
    "servicePhone": "800344225"
  },
  "birthday": "1997-10-18T19:41:54.260Z",
  "ip": "161.112.189.186",
  "foo": "bar",
  "profile": {
    "about": "Rup vagfasli vucluwjep ovalascir zal ci ojdiban kengav bubpis jaci eszaf ub hikutiz livtef bodtuw junimiur picdoj rufjok. Asauwukih elo sipow fenko logeh sodjijsi poduzo kehzosiwo kucun ehevela izoduto asogob igicosaz vovo. Goajafag juduv omtas ebi araji fewu de pu afca situr zezibi moci naniju foregev butaja ud.",
    "bio": "Cujke zadvil uz sizo fa led aw teuko dufesmo bojis refguz uh zos jaeg. Cihosu zactun us coasbad hepto umra vir lom ogzuwet geca rait remeli hifhefa en dedralgar he rehujim golasaz. Dewu rerbili dogocta esomaso zezviti ihufotid datco icezok wizate zakziezo fu muh tifivvo muw efanol dihos. Ob im uliode nesiti egaorihoh udil wa lik lupwaene wofa he raduside vacvipsi tapawi wu."
  },
  "apiKey": "522e7f4dc5fee83ee1992a75eb47a06a2f1cd91ac798dff3079407ce1f707a9a",
  "currency": {
    "code": "SVC",
    "name": "El Salvador Colon"
  }
}