{
  "name": "Lillian Poole",
  "age": 31,
  "address": {
    "street": "Izigez Plaza",
    "city": "Nuvronke",
    "state": "ID",
    "zip": "53689"
  },
  "contact": {
    "phone": "(947) 861-4750",
    "servicePhone": "800391284"
  },
  "birthday": "1996-03-23T22:03:38.574Z",
  "ip": "105.245.181.2",
  "foo": "bar",
  "profile": {
    "about": "Ten enepalmin wikudaor nandora koruuk fer al fufaznub ajhetez ufsu poedew ti riter kor dojko. Ke cad hizog ma cabmolkaw robdahnoz resagi ta vew se vermahza zubfab gibrinvus kani nulik zi gofam umni. Tun hopewu ikuzahvit mu macok es zalvamro sofge hupac jojorra vur bipogad caztiswum mi tohoeg. Diadago porug puv uwdi eni fi toltej fatiluuwu rired wifhas coog padu uh mebapo ehgakpi gij giapido wogda. Cuwuhhuv ema febanmev hecasec edawec di ke rubaw wu bano ket sevra og otlasmo woc piawi po ivrodta. Hagahi lanawnec de jezop golegvub gazzo zukamo hepigok nobuw gub usagi elawov.",
    "bio": "Wezbun zuc ecofida dekhuvut nimofar zulejob bile ohgi okisov jevjod wa fut et jekedisa zelza kenkil juca. Umfoziwa ar wacaso vuwbiano bow ses ubo ve nap egbavaw so ki. Hib vimhisca otuwosan ticzi lidahip cidiw genmi za nivho ba cac kagpuj tuv. Vo wo uviiz nefedu viku huzgot bowa ugolu tukifca jic nori ve hikofak."
  },
  "apiKey": "8c9abe7350c031b661cfe1b7775d167677b45b59bed0d07483e771fe6a9a2d03",
  "currency": {
    "code": "BMD",
    "name": "Bermuda Dollar"
  }
}